3/cnn_input_sram.sv
`timescale 1ns/1ps

module cnn_input_sram (
    input  wire        clk,

    input  wire        write_en,
    input  wire [1:0]  write_bank,
    input  wire [13:0] write_addr,
    input  wire [7:0]  write_data,

    input  wire        read_en,
    input  wire [7:0]  start_row,
    input  wire [7:0]  start_col,

    output reg  [23:0] cnn_data,
    output reg         out_valid,

    output wire [1:0]  bank0,
    output wire [1:0]  bank1,
    output wire [1:0]  bank2,

    output wire [13:0] addr0,
    output wire [13:0] addr1,
    output wire [13:0] addr2,

    output wire [7:0]  pixel0,
    output wire [7:0]  pixel1,
    output wire [7:0]  pixel2
);

    // =========================================================
    // 64 KB SRAM
    // 4 banks x 16 KB
    // =========================================================

    reg [7:0] mem [0:65535];

    // =========================================================
    // WRITE
    //
    // Physical address:
    // bank 0 -> 0x0000 - 0x3FFF
    // bank 1 -> 0x4000 - 0x7FFF
    // bank 2 -> 0x8000 - 0xBFFF
    // bank 3 -> 0xC000 - 0xFFFF
    // =========================================================

    wire [15:0] write_phys_addr;

    assign write_phys_addr =
        {write_bank, write_addr};

    always @(posedge clk) begin
        if (write_en)
            mem[write_phys_addr] <= write_data;
    end

    // =========================================================
    // THREE-PIXEL CNN WINDOW
    //
    // Pixel 0 = (start_row, start_col)
    // Pixel 1 = (start_row, start_col+1)
    // Pixel 2 = (start_row, start_col+2)
    // =========================================================

    wire [8:0] col0;
    wire [8:0] col1;
    wire [8:0] col2;

    assign col0 = {1'b0,start_col};
    assign col1 = {1'b0,start_col} + 9'd1;
    assign col2 = {1'b0,start_col} + 9'd2;

    // =========================================================
    // STAGGERED BANK SELECTION
    //
    // column 0 -> bank 0
    // column 1 -> bank 1
    // column 2 -> bank 2
    // column 3 -> bank 3
    // column 4 -> bank 0
    // ...
    // =========================================================

    assign bank0 = col0[1:0];
    assign bank1 = col1[1:0];
    assign bank2 = col2[1:0];

    // =========================================================
    // LOCAL ADDRESS INSIDE EACH BANK
    //
    // 256 rows x 64 bytes
    //
    // address = row*64 + column/4
    // =========================================================

    assign addr0 =
        (start_row << 6) + col0[8:2];

    assign addr1 =
        (start_row << 6) + col1[8:2];

    assign addr2 =
        (start_row << 6) + col2[8:2];

    // =========================================================
    // PHYSICAL ADDRESSES
    // =========================================================

    wire [15:0] phys0;
    wire [15:0] phys1;
    wire [15:0] phys2;

    assign phys0 = {bank0,addr0};
    assign phys1 = {bank1,addr1};
    assign phys2 = {bank2,addr2};

    // =========================================================
    // READ PIXELS
    // =========================================================

    assign pixel0 = mem[phys0];
    assign pixel1 = mem[phys1];
    assign pixel2 = mem[phys2];

    // =========================================================
    // 24-BIT OUTPUT
    // =========================================================

    always @(posedge clk) begin

        if (read_en) begin
            cnn_data  <= {pixel0,pixel1,pixel2};
            out_valid <= 1'b1;
        end
        else begin
            cnn_data  <= 24'h000000;
            out_valid <= 1'b0;
        end

    end

endmodule

3/tb_cnn_input_sram.sv
`timescale 1ns/1ps

// ============================================================
// QUESTION 3 TESTBENCH
//
// Verifies:
// 1. Four-bank SRAM organization
// 2. Staggered address mapping
// 3. Bank selection
// 4. CNN read control
// 5. 24-bit output
// ============================================================

module tb_cnn_input_sram;

    reg clk;

    // Write interface
    reg        write_en;
    reg [1:0]  write_bank;
    reg [13:0] write_addr;
    reg [7:0]  write_data;

    // CNN read interface
    reg        read_en;
    reg [7:0]  start_row;
    reg [7:0]  start_col;

    // Outputs
    wire [23:0] cnn_data;
    wire        out_valid;

    wire [1:0]  bank0;
    wire [1:0]  bank1;
    wire [1:0]  bank2;

    wire [13:0] addr0;
    wire [13:0] addr1;
    wire [13:0] addr2;

    wire [7:0] pixel0;
    wire [7:0] pixel1;
    wire [7:0] pixel2;

    integer errors;

    // ========================================================
    // DUT
    // ========================================================

    cnn_input_sram dut (

        .clk(clk),

        .write_en(write_en),
        .write_bank(write_bank),
        .write_addr(write_addr),
        .write_data(write_data),

        .read_en(read_en),
        .start_row(start_row),
        .start_col(start_col),

        .cnn_data(cnn_data),
        .out_valid(out_valid),

        .bank0(bank0),
        .bank1(bank1),
        .bank2(bank2),

        .addr0(addr0),
        .addr1(addr1),
        .addr2(addr2),

        .pixel0(pixel0),
        .pixel1(pixel1),
        .pixel2(pixel2)
    );

    // ========================================================
    // CLOCK
    // ========================================================

    initial begin
        clk = 1'b0;

        forever #5 clk = ~clk;
    end

    // ========================================================
    // WRITE TASK
    // ========================================================

    task write_pixel;

        input [7:0] row;
        input [7:0] col;
        input [7:0] data;

        integer bank_number;
        integer local_col;
        integer memory_address;

        begin

            bank_number = col % 4;
            local_col = col / 4;
            memory_address = row * 64 + local_col;

            @(negedge clk);

            write_en   = 1'b1;
            write_bank = bank_number;
            write_addr = memory_address;
            write_data = data;

            @(posedge clk);

            #1;

            write_en = 1'b0;

        end

    endtask

    // ========================================================
    // READ / VERIFY TASK
    // ========================================================

    task read_window;

        input [7:0] row;
        input [7:0] col;

        input [7:0] expected0;
        input [7:0] expected1;
        input [7:0] expected2;

        reg [23:0] expected;

        begin

            expected = {expected0, expected1, expected2};

            @(negedge clk);

            start_row = row;
            start_col = col;
            read_en   = 1'b1;

            @(posedge clk);

            #1;

            $display("");
            $display("--------------------------------------------------");
            $display("CNN READ");
            $display("Start Row       = %0d", row);
            $display("Start Column    = %0d", col);

            $display("Pixel 0         = 0x%02h", pixel0);
            $display("Pixel 1         = 0x%02h", pixel1);
            $display("Pixel 2         = 0x%02h", pixel2);

            $display("Bank selection  = %0d, %0d, %0d",
                     bank0, bank1, bank2);

            $display("Address         = %0d, %0d, %0d",
                     addr0, addr1, addr2);

            $display("Expected output = 0x%06h", expected);
            $display("Actual output   = 0x%06h", cnn_data);

            if ((cnn_data === expected) &&
                (out_valid === 1'b1)) begin

                $display("RESULT          = PASS");

            end
            else begin

                $display("RESULT          = FAIL");
                errors = errors + 1;

            end

            read_en = 1'b0;

        end

    endtask

    // ========================================================
    // TEST
    // ========================================================

    initial begin

        errors = 0;

        write_en   = 1'b0;
        write_bank = 2'd0;
        write_addr = 14'd0;
        write_data = 8'h00;

        read_en   = 1'b0;
        start_row = 8'd0;
        start_col = 8'd0;

        // ====================================================
        // VCD
        // ====================================================

        $dumpfile("cnn_input_sram.vcd");
        $dumpvars(0, tb_cnn_input_sram);

        // ====================================================
        // Header
        // ====================================================

        $display("");
        $display("==================================================");
        $display("       QUESTION 3 - CNN INPUT SRAM");
        $display("==================================================");
        $display("Image       : 256 x 256");
        $display("Pixel       : 8 bits");
        $display("Banks       : 4");
        $display("Bank size   : 256 x 64 bytes");
        $display("Output      : 24 bits");
        $display("==================================================");

        // ====================================================
        // WRITE KNOWN PIXELS
        //
        // Row 0:
        //
        // col 0 = A0
        // col 1 = A1
        // col 2 = A2
        // col 3 = A3
        // col 4 = A4
        // col 5 = A5
        // col 6 = A6
        // col 7 = A7
        // col 8 = A8
        // col 9 = A9
        // ====================================================

        write_pixel(8'd0, 8'd0, 8'hA0);
        write_pixel(8'd0, 8'd1, 8'hA1);
        write_pixel(8'd0, 8'd2, 8'hA2);
        write_pixel(8'd0, 8'd3, 8'hA3);
        write_pixel(8'd0, 8'd4, 8'hA4);
        write_pixel(8'd0, 8'd5, 8'hA5);
        write_pixel(8'd0, 8'd6, 8'hA6);
        write_pixel(8'd0, 8'd7, 8'hA7);
        write_pixel(8'd0, 8'd8, 8'hA8);
        write_pixel(8'd0, 8'd9, 8'hA9);

        // ====================================================
        // Row 1
        // ====================================================

        write_pixel(8'd1, 8'd0, 8'hB0);
        write_pixel(8'd1, 8'd1, 8'hB1);
        write_pixel(8'd1, 8'd2, 8'hB2);
        write_pixel(8'd1, 8'd3, 8'hB3);
        write_pixel(8'd1, 8'd4, 8'hB4);
        write_pixel(8'd1, 8'd5, 8'hB5);

        // ====================================================
        // READ WINDOWS
        // ====================================================

        // --------------------------------------------
        // Window 1: columns 0,1,2
        // Banks = 0,1,2
        // --------------------------------------------

        read_window(
            8'd0,
            8'd0,
            8'hA0,
            8'hA1,
            8'hA2
        );

        // --------------------------------------------
        // Window 2: columns 1,2,3
        // Banks = 1,2,3
        // --------------------------------------------

        read_window(
            8'd0,
            8'd1,
            8'hA1,
            8'hA2,
            8'hA3
        );

        // --------------------------------------------
        // Window 3: columns 2,3,4
        // Banks = 2,3,0
        // --------------------------------------------

        read_window(
            8'd0,
            8'd2,
            8'hA2,
            8'hA3,
            8'hA4
        );

        // --------------------------------------------
        // Window 4: columns 3,4,5
        // Banks = 3,0,1
        // --------------------------------------------

        read_window(
            8'd0,
            8'd3,
            8'hA3,
            8'hA4,
            8'hA5
        );

        // --------------------------------------------
        // Window 5: columns 7,8,9
        // Banks = 3,0,1
        // --------------------------------------------

        read_window(
            8'd0,
            8'd7,
            8'hA7,
            8'hA8,
            8'hA9
        );

        // --------------------------------------------
        // Window 6: second row
        // --------------------------------------------

        read_window(
            8'd1,
            8'd0,
            8'hB0,
            8'hB1,
            8'hB2
        );

        // ====================================================
        // FINAL RESULT
        // ====================================================

        $display("");
        $display("==================================================");

        if (errors == 0) begin

            $display("       QUESTION 3 TEST PASSED");
            $display("       CNN ADDRESS GENERATION : PASS");
            $display("       BANK SELECTION         : PASS");
            $display("       READ CONTROL           : PASS");
            $display("       24-BIT OUTPUT          : PASS");

        end
        else begin

            $display("       QUESTION 3 TEST FAILED");
            $display("       ERRORS = %0d", errors);

        end

        $display("==================================================");
        $display("");

        #20;

        $finish;

    end

endmodule

3/cnn_input_sram.vcd
$date
	Sat Sep 26 06:07:28 2026
$end
$version
	Icarus Verilog
$end
$timescale
	1ps
$end
$scope module tb_cnn_input_sram $end
$var wire 8 ! pixel2 [7:0] $end
$var wire 8 " pixel1 [7:0] $end
$var wire 8 # pixel0 [7:0] $end
$var wire 1 $ out_valid $end
$var wire 24 % cnn_data [23:0] $end
$var wire 2 & bank2 [1:0] $end
$var wire 2 ' bank1 [1:0] $end
$var wire 2 ( bank0 [1:0] $end
$var wire 14 ) addr2 [13:0] $end
$var wire 14 * addr1 [13:0] $end
$var wire 14 + addr0 [13:0] $end
$var reg 1 , clk $end
$var reg 1 - read_en $end
$var reg 8 . start_col [7:0] $end
$var reg 8 / start_row [7:0] $end
$var reg 14 0 write_addr [13:0] $end
$var reg 2 1 write_bank [1:0] $end
$var reg 8 2 write_data [7:0] $end
$var reg 1 3 write_en $end
$var integer 32 4 errors [31:0] $end
$scope module dut $end
$var wire 1 , clk $end
$var wire 8 5 pixel0 [7:0] $end
$var wire 8 6 pixel1 [7:0] $end
$var wire 8 7 pixel2 [7:0] $end
$var wire 1 - read_en $end
$var wire 8 8 start_col [7:0] $end
$var wire 8 9 start_row [7:0] $end
$var wire 14 : write_addr [13:0] $end
$var wire 2 ; write_bank [1:0] $end
$var wire 8 < write_data [7:0] $end
$var wire 1 3 write_en $end
$var wire 16 = write_phys_addr [15:0] $end
$var wire 16 > phys2 [15:0] $end
$var wire 16 ? phys1 [15:0] $end
$var wire 16 @ phys0 [15:0] $end
$var wire 9 A col2 [8:0] $end
$var wire 9 B col1 [8:0] $end
$var wire 9 C col0 [8:0] $end
$var wire 2 D bank2 [1:0] $end
$var wire 2 E bank1 [1:0] $end
$var wire 2 F bank0 [1:0] $end
$var wire 14 G addr2 [13:0] $end
$var wire 14 H addr1 [13:0] $end
$var wire 14 I addr0 [13:0] $end
$var reg 24 J cnn_data [23:0] $end
$var reg 1 $ out_valid $end
$upscope $end
$scope task read_window $end
$var reg 8 K col [7:0] $end
$var reg 24 L expected [23:0] $end
$var reg 8 M expected0 [7:0] $end
$var reg 8 N expected1 [7:0] $end
$var reg 8 O expected2 [7:0] $end
$var reg 8 P row [7:0] $end
$upscope $end
$scope task write_pixel $end
$var reg 8 Q col [7:0] $end
$var reg 8 R data [7:0] $end
$var reg 8 S row [7:0] $end
$var integer 32 T bank_number [31:0] $end
$var integer 32 U local_col [31:0] $end
$var integer 32 V memory_address [31:0] $end
$upscope $end
$upscope $end
$enddefinitions $end
$comment Show the parameter values. $end
$dumpall
$end
#0
$dumpvars
b0 V
b0 U
b0 T
b0 S
b10100000 R
b0 Q
bx P
bx O
bx N
bx M
bx L
bx K
bx J
b0 I
b0 H
b0 G
b0 F
b1 E
b10 D
b0 C
b1 B
b10 A
b0 @
b100000000000000 ?
b1000000000000000 >
b0 =
b0 <
b0 ;
b0 :
b0 9
b0 8
bx 7
bx 6
bx 5
b0 4
03
b0 2
b0 1
b0 0
b0 /
b0 .
0-
0,
b0 +
b0 *
b0 )
b0 (
b1 '
b10 &
bx %
x$
bx #
bx "
bx !
$end
#5000
0$
b0 %
b0 J
1,
#10000
b10100000 2
b10100000 <
13
0,
#15000
b10100000 #
b10100000 5
1,
#16000
b1 T
b10100001 R
b1 Q
03
#20000
b10100001 2
b10100001 <
b100000000000000 =
b1 1
b1 ;
13
0,
#25000
b10100001 "
b10100001 6
1,
#26000
b10 T
b10100010 R
b10 Q
03
#30000
b10100010 2
b10100010 <
b1000000000000000 =
b10 1
b10 ;
13
0,
#35000
b10100010 !
b10100010 7
1,
#36000
b11 T
b10100011 R
b11 Q
03
#40000
b10100011 2
b10100011 <
b1100000000000000 =
b11 1
b11 ;
13
0,
#45000
1,
#46000
b1 V
b1 U
b0 T
b10100100 R
b100 Q
03
#50000
b10100100 2
b10100100 <
b1 0
b1 :
b1 =
b0 1
b0 ;
13
0,
#55000
1,
#56000
b1 T
b10100101 R
b101 Q
03
#60000
b10100101 2
b10100101 <
b100000000000001 =
b1 1
b1 ;
13
0,
#65000
1,
#66000
b10 T
b10100110 R
b110 Q
03
#70000
b10100110 2
b10100110 <
b1000000000000001 =
b10 1
b10 ;
13
0,
#75000
1,
#76000
b11 T
b10100111 R
b111 Q
03
#80000
b10100111 2
b10100111 <
b1100000000000001 =
b11 1
b11 ;
13
0,
#85000
1,
#86000
b10 V
b10 U
b0 T
b10101000 R
b1000 Q
03
#90000
b10101000 2
b10101000 <
b10 0
b10 :
b10 =
b0 1
b0 ;
13
0,
#95000
1,
#96000
b1 T
b10101001 R
b1001 Q
03
#100000
b10101001 2
b10101001 <
b100000000000010 =
b1 1
b1 ;
13
0,
#105000
1,
#106000
b1000000 V
b0 U
b0 T
b10110000 R
b0 Q
b1 S
03
#110000
b10110000 2
b10110000 <
b1000000 0
b1000000 :
b1000000 =
b0 1
b0 ;
13
0,
#115000
1,
#116000
b1 T
b10110001 R
b1 Q
03
#120000
b10110001 2
b10110001 <
b100000001000000 =
b1 1
b1 ;
13
0,
#125000
1,
#126000
b10 T
b10110010 R
b10 Q
03
#130000
b10110010 2
b10110010 <
b1000000001000000 =
b10 1
b10 ;
13
0,
#135000
1,
#136000
b11 T
b10110011 R
b11 Q
03
#140000
b10110011 2
b10110011 <
b1100000001000000 =
b11 1
b11 ;
13
0,
#145000
1,
#146000
b1000001 V
b1 U
b0 T
b10110100 R
b100 Q
03
#150000
b10110100 2
b10110100 <
b1000001 0
b1000001 :
b1000001 =
b0 1
b0 ;
13
0,
#155000
1,
#156000
b1 T
b10110101 R
b101 Q
03
#160000
b10110101 2
b10110101 <
b100000001000001 =
b1 1
b1 ;
13
0,
#165000
1,
#166000
b101000001010000110100010 L
b10100010 O
b10100001 N
b10100000 M
b0 K
b0 P
03
#170000
1-
0,
#175000
1$
b101000001010000110100010 %
b101000001010000110100010 J
1,
#176000
b101000011010001010100011 L
b10100011 O
b10100010 N
b10100001 M
b1 K
0-
#180000
b10100001 #
b10100001 5
b100000000000000 @
b1 (
b1 F
b10100010 "
b10100010 6
b1000000000000000 ?
b10 '
b10 E
b10100011 !
b10100011 7
b1100000000000000 >
b11 &
b11 D
1-
b1 C
b10 B
b11 A
b1 .
b1 8
0,
#185000
b101000011010001010100011 %
b101000011010001010100011 J
1,
#186000
b101000101010001110100100 L
b10100100 O
b10100011 N
b10100010 M
b10 K
0-
#190000
b10100010 #
b10100010 5
b1000000000000000 @
b10 (
b10 F
b10100011 "
b10100011 6
b1100000000000000 ?
b11 '
b11 E
b0 &
b0 D
b10100100 !
b10100100 7
b1 >
b1 )
b1 G
1-
b10 C
b11 B
b100 A
b10 .
b10 8
0,
#195000
b101000101010001110100100 %
b101000101010001110100100 J
1,
#196000
b101000111010010010100101 L
b10100101 O
b10100100 N
b10100011 M
b11 K
0-
#200000
b10100011 #
b10100011 5
b1100000000000000 @
b11 (
b11 F
b0 '
b0 E
b10100100 "
b10100100 6
b1 ?
b1 *
b1 H
b10100101 !
b10100101 7
b100000000000001 >
b1 &
b1 D
1-
b11 C
b100 B
b101 A
b11 .
b11 8
0,
#205000
b101000111010010010100101 %
b101000111010010010100101 J
1,
#206000
b101001111010100010101001 L
b10101001 O
b10101000 N
b10100111 M
b111 K
0-
#210000
b10100111 #
b10100111 5
b1100000000000001 @
b1 +
b1 I
b10101000 "
b10101000 6
b10 ?
b10 *
b10 H
b10101001 !
b10101001 7
b100000000000010 >
b10 )
b10 G
1-
b111 C
b1000 B
b1001 A
b111 .
b111 8
0,
#215000
b101001111010100010101001 %
b101001111010100010101001 J
1,
#216000
b101100001011000110110010 L
b10110010 O
b10110001 N
b10110000 M
b0 K
b1 P
0-
#220000
b0 (
b0 F
b1 '
b1 E
b10 &
b10 D
b10110000 #
b10110000 5
b1000000 @
b1000000 +
b1000000 I
b10110001 "
b10110001 6
b100000001000000 ?
b1000000 *
b1000000 H
b10110010 !
b10110010 7
b1000000001000000 >
b1000000 )
b1000000 G
1-
b0 C
b1 B
b10 A
b0 .
b0 8
b1 /
b1 9
0,
#225000
b101100001011000110110010 %
b101100001011000110110010 J
1,
#226000
0-
#230000
0,
#235000
0$
b0 %
b0 J
1,
