2/4banks/sram_4banks.sv
`timescale 1ns/1ps

module sram_4banks (
    input  logic        clk,
    input  logic        we,
    input  logic        re,

    // 14-bit 32-bit-word address
    //
    // [13:12] = bank select
    // [11:4]  = row address
    // [3:0]   = word select within 512-bit row
    input  logic [13:0] addr,

    input  logic [31:0] wdata,
    output logic [31:0] rdata,

    output logic [1:0] bank_sel
);

    // =========================================================
    // FOUR-BANK SRAM
    //
    // Each bank:
    //     256 rows x 512 bits
    //
    // Each 512-bit row contains:
    //     512 / 32 = 16 words
    //
    // Therefore:
    //     256 x 16 = 4096 words
    //
    // Each bank:
    //     4096 x 4 bytes = 16384 bytes = 16 KB
    //
    // Four banks:
    //     4 x 16 KB = 64 KB
    // =========================================================

    logic [511:0] bank0 [0:255];
    logic [511:0] bank1 [0:255];
    logic [511:0] bank2 [0:255];
    logic [511:0] bank3 [0:255];

    // =========================================================
    // ADDRESS DECODING
    // =========================================================

    logic [7:0] row_addr;
    logic [3:0] word_sel;

    assign bank_sel = addr[13:12];
    assign row_addr = addr[11:4];
    assign word_sel = addr[3:0];

    // =========================================================
    // WRITE OPERATION
    // =========================================================

    always_ff @(posedge clk) begin

        if (we) begin

            case (bank_sel)

                2'd0: begin
                    bank0[row_addr][word_sel*32 +: 32] <= wdata;
                end

                2'd1: begin
                    bank1[row_addr][word_sel*32 +: 32] <= wdata;
                end

                2'd2: begin
                    bank2[row_addr][word_sel*32 +: 32] <= wdata;
                end

                2'd3: begin
                    bank3[row_addr][word_sel*32 +: 32] <= wdata;
                end

            endcase

        end

    end

    // =========================================================
    // READ OPERATION
    // =========================================================

    always_comb begin

        rdata = 32'b0;

        if (re) begin

            case (bank_sel)

                2'd0: begin
                    rdata = bank0[row_addr][word_sel*32 +: 32];
                end

                2'd1: begin
                    rdata = bank1[row_addr][word_sel*32 +: 32];
                end

                2'd2: begin
                    rdata = bank2[row_addr][word_sel*32 +: 32];
                end

                2'd3: begin
                    rdata = bank3[row_addr][word_sel*32 +: 32];
                end

            endcase

        end

    end

endmodule

2/4banks/tb_sram_4banks.sv
`timescale 1ns/1ps

module tb_sram_4banks;

    logic        clk;
    logic        we;
    logic        re;
    logic [13:0] addr;
    logic [31:0] wdata;
    logic [31:0] rdata;
    logic [1:0]  bank_sel;

    integer i;
    integer errors;

    logic [13:0] test_addr [0:3];
    logic [31:0] test_data [0:3];

    // =========================================================
    // DUT
    // =========================================================

    sram_4banks dut (
        .clk      (clk),
        .we       (we),
        .re       (re),
        .addr     (addr),
        .wdata     (wdata),
        .rdata     (rdata),
        .bank_sel (bank_sel)
    );

    // =========================================================
    // CLOCK
    // =========================================================

    initial begin
        clk = 1'b0;
        forever #5 clk = ~clk;
    end

    // =========================================================
    // TEST
    // =========================================================

    initial begin

        $dumpfile("sram_4banks.vcd");
        $dumpvars(0, tb_sram_4banks);

        we    = 1'b0;
        re    = 1'b0;
        addr  = 14'd0;
        wdata = 32'd0;

        errors = 0;

        // =====================================================
        // ONE LOCATION IN EACH BANK
        //
        // Same row and word position:
        //
        // Bank 0 -> 0x0005
        // Bank 1 -> 0x1005
        // Bank 2 -> 0x2005
        // Bank 3 -> 0x3005
        // =====================================================

        test_addr[0] = 14'h0005;
        test_addr[1] = 14'h1005;
        test_addr[2] = 14'h2005;
        test_addr[3] = 14'h3005;

        test_data[0] = 32'h11111111;
        test_data[1] = 32'h22222222;
        test_data[2] = 32'h33333333;
        test_data[3] = 32'h44444444;

        #10;

        // =====================================================
        // WRITE
        // =====================================================

        $display("");
        $display("==============================================");
        $display("       Q2(ii) FOUR-BANK SRAM WRITE");
        $display("==============================================");

        we = 1'b1;
        re = 1'b0;

        for (i = 0; i < 4; i = i + 1) begin

            @(negedge clk);

            addr  = test_addr[i];
            wdata = test_data[i];

            @(posedge clk);

            #1;

            $display(
                "WRITE | bank=%0d | addr=0x%04h | row=%0d | word=%0d | data=0x%08h",
                bank_sel,
                addr,
                addr[11:4],
                addr[3:0],
                wdata
            );

        end

        @(negedge clk);

        we = 1'b0;

        // =====================================================
        // READ AND VERIFY
        // =====================================================

        $display("");
        $display("==============================================");
        $display("       Q2(ii) FOUR-BANK SRAM READ");
        $display("==============================================");

        re = 1'b1;

        for (i = 0; i < 4; i = i + 1) begin

            @(negedge clk);

            addr = test_addr[i];

            #1;

            if (rdata === test_data[i]) begin

                $display(
                    "READ  | bank=%0d | addr=0x%04h | expected=0x%08h | actual=0x%08h | PASS",
                    bank_sel,
                    addr,
                    test_data[i],
                    rdata
                );

            end
            else begin

                $display(
                    "READ  | bank=%0d | addr=0x%04h | expected=0x%08h | actual=0x%08h | FAIL",
                    bank_sel,
                    addr,
                    test_data[i],
                    rdata
                );

                errors = errors + 1;

            end

        end

        // =====================================================
        // FINAL RESULT
        // =====================================================

        $display("");
        $display("==============================================");

        if (errors == 0) begin

            $display("       ASSIGNMENT 2(ii) TEST PASSED");
            $display("       ALL 4 BANKS VERIFIED");

        end
        else begin

            $display("       ASSIGNMENT 2(ii) TEST FAILED");
            $display("       ERRORS = %0d", errors);

        end

        $display("==============================================");
        $display("");

        re = 1'b0;

        #20;

        $finish;

    end

endmodule

2/4banks/sram_4banks.vcd
$date
	Sat Sep 26 05:44:22 2026
$end
$version
	Icarus Verilog
$end
$timescale
	1ps
$end
$scope module tb_sram_4banks $end
$var wire 32 ! rdata [31:0] $end
$var wire 2 " bank_sel [1:0] $end
$var reg 14 # addr [13:0] $end
$var reg 1 $ clk $end
$var reg 1 % re $end
$var reg 32 & wdata [31:0] $end
$var reg 1 ' we $end
$var integer 32 ( errors [31:0] $end
$var integer 32 ) i [31:0] $end
$scope module dut $end
$var wire 14 * addr [13:0] $end
$var wire 1 $ clk $end
$var wire 1 % re $end
$var wire 32 + wdata [31:0] $end
$var wire 1 ' we $end
$var wire 4 , word_sel [3:0] $end
$var wire 8 - row_addr [7:0] $end
$var wire 2 . bank_sel [1:0] $end
$var reg 32 / rdata [31:0] $end
$upscope $end
$upscope $end
$enddefinitions $end
$comment Show the parameter values. $end
$dumpall
$end
#0
$dumpvars
b0 /
b0 .
b0 -
b0 ,
b0 +
b0 *
bx )
b0 (
0'
b0 &
0%
0$
b0 #
b0 "
b0 !
$end
#5000
1$
#10000
b101 ,
b10001000100010001000100010001 &
b10001000100010001000100010001 +
b101 #
b101 *
0$
b0 )
1'
#15000
1$
#16000
b1 )
#20000
b1 "
b1 .
b100010001000100010001000100010 &
b100010001000100010001000100010 +
b1000000000101 #
b1000000000101 *
0$
#25000
1$
#26000
b10 )
#30000
b10 "
b10 .
b110011001100110011001100110011 &
b110011001100110011001100110011 +
b10000000000101 #
b10000000000101 *
0$
#35000
1$
#36000
b11 )
#40000
b11 "
b11 .
b1000100010001000100010001000100 &
b1000100010001000100010001000100 +
b11000000000101 #
b11000000000101 *
0$
#45000
1$
#46000
b100 )
#50000
b1000100010001000100010001000100 !
b1000100010001000100010001000100 /
b0 )
1%
0'
0$
#55000
1$
#60000
b10001000100010001000100010001 !
b10001000100010001000100010001 /
b0 "
b0 .
b101 #
b101 *
0$
#61000
b1 )
#65000
1$
#70000
b100010001000100010001000100010 !
b100010001000100010001000100010 /
b1 "
b1 .
b1000000000101 #
b1000000000101 *
0$
#71000
b10 )
#75000
1$
#80000
b110011001100110011001100110011 !
b110011001100110011001100110011 /
b10 "
b10 .
b10000000000101 #
b10000000000101 *
0$
#81000
b11 )
#85000
1$
#90000
b1000100010001000100010001000100 !
b1000100010001000100010001000100 /
b11 "
b11 .
b11000000000101 #
b11000000000101 *
0$
#91000
b0 !
b0 /
0%
b100 )
