2/consolidated/sram_64kb.sv
`timescale 1ns/1ps

module sram_64kb (
    input  logic        clk,
    input  logic        we,
    input  logic        re,
    input  logic [13:0] addr,
    input  logic [31:0] wdata,
    output logic [31:0] rdata
);

    // =========================================================
    // 64 KB SRAM
    //
    // Physical array:
    //     1024 rows x 512 bits
    //
    // 512 bits / 32 bits = 16 words per row
    //
    // Total:
    //     1024 x 16 = 16384 words
    //     16384 x 4 bytes = 65536 bytes = 64 KB
    // =========================================================

    logic [511:0] mem [0:1023];

    logic [9:0]  row_addr;
    logic [3:0]  word_sel;

    assign row_addr = addr[13:4];
    assign word_sel = addr[3:0];

    // =========================================================
    // WRITE
    // =========================================================

    always_ff @(posedge clk) begin

        if (we) begin

            mem[row_addr][word_sel*32 +: 32] <= wdata;

        end

    end

    // =========================================================
    // READ
    // =========================================================

    always_comb begin

        if (re) begin

            rdata = mem[row_addr][word_sel*32 +: 32];

        end
        else begin

            rdata = 32'b0;

        end

    end

endmodule

2/consolidated/tb_sram_64kb.sv
`timescale 1ns/1ps

module tb_sram_64kb;

    logic        clk;
    logic        we;
    logic        re;
    logic [13:0] addr;
    logic [31:0] wdata;
    logic [31:0] rdata;

    integer i;
    integer errors;

    // ---------------------------------------------------------
    // Test addresses
    // ---------------------------------------------------------

    logic [13:0] test_addr [0:7];
    logic [31:0] test_data [0:7];

    // ---------------------------------------------------------
    // DUT
    // ---------------------------------------------------------

    sram_64kb dut (
        .clk   (clk),
        .we    (we),
        .re    (re),
        .addr  (addr),
        .wdata (wdata),
        .rdata (rdata)
    );

    // ---------------------------------------------------------
    // Clock
    // ---------------------------------------------------------

    initial begin
        clk = 1'b0;

        forever #5 clk = ~clk;
    end

    // ---------------------------------------------------------
    // Test
    // ---------------------------------------------------------

    initial begin

        $dumpfile("sram_64kb.vcd");
        $dumpvars(0, tb_sram_64kb);

        we = 1'b0;
        re = 1'b0;
        addr = 14'd0;
        wdata = 32'd0;

        errors = 0;

        // -----------------------------------------------------
        // Eight test locations
        // -----------------------------------------------------

        test_addr[0] = 14'd0;
        test_addr[1] = 14'd1;
        test_addr[2] = 14'd15;
        test_addr[3] = 14'd16;
        test_addr[4] = 14'd100;
        test_addr[5] = 14'd1023;
        test_addr[6] = 14'd4095;
        test_addr[7] = 14'd16383;

        test_data[0] = 32'hA5A50001;
        test_data[1] = 32'hA5A50002;
        test_data[2] = 32'hA5A50003;
        test_data[3] = 32'hA5A50004;
        test_data[4] = 32'hA5A50005;
        test_data[5] = 32'hA5A50006;
        test_data[6] = 32'hA5A50007;
        test_data[7] = 32'hA5A50008;

        // -----------------------------------------------------
        // RESET / INITIALIZATION
        // -----------------------------------------------------

        #10;

        // =====================================================
        // WRITE 8 LOCATIONS
        // =====================================================

        $display("");
        $display("==============================================");
        $display("       Q2(i) SRAM WRITE OPERATION");
        $display("==============================================");

        we = 1'b1;
        re = 1'b0;

        for (i = 0; i < 8; i = i + 1) begin

            @(negedge clk);

            addr  = test_addr[i];
            wdata = test_data[i];

            @(posedge clk);

            #1;

            $display(
                "WRITE | addr=%0d | row=%0d | word=%0d | data=0x%08h",
                addr,
                addr >> 4,
                addr & 14'h000F,
                wdata
            );

        end

        // Stop writing
        @(negedge clk);

        we = 1'b0;

        // =====================================================
        // READ AND VERIFY 8 LOCATIONS
        // =====================================================

        $display("");
        $display("==============================================");
        $display("       Q2(i) SRAM READ / VERIFY");
        $display("==============================================");

        re = 1'b1;

        for (i = 0; i < 8; i = i + 1) begin

            @(negedge clk);

            addr = test_addr[i];

            #1;

            if (rdata === test_data[i]) begin

                $display(
                    "READ  | addr=%0d | expected=0x%08h | actual=0x%08h | PASS",
                    addr,
                    test_data[i],
                    rdata
                );

            end
            else begin

                $display(
                    "READ  | addr=%0d | expected=0x%08h | actual=0x%08h | FAIL",
                    addr,
                    test_data[i],
                    rdata
                );

                errors = errors + 1;

            end

        end

        // =====================================================
        // FINAL RESULT
        // =====================================================

        $display("");
        $display("==============================================");

        if (errors == 0) begin

            $display("       ASSIGNMENT 2(i) TEST PASSED");
            $display("       64 KB CONSOLIDATED SRAM");
            $display("       8 LOCATIONS VERIFIED");

        end
        else begin

            $display("       ASSIGNMENT 2(i) TEST FAILED");
            $display("       ERRORS = %0d", errors);

        end

        $display("==============================================");
        $display("");

        re = 1'b0;

        #20;

        $finish;

    end

endmodule

2/consolidated/sram_64kb.vcd
$date
	Sat Sep 26 05:37:22 2026
$end
$version
	Icarus Verilog
$end
$timescale
	1ps
$end
$scope module tb_sram_64kb $end
$var wire 32 ! rdata [31:0] $end
$var reg 14 " addr [13:0] $end
$var reg 1 # clk $end
$var reg 1 $ re $end
$var reg 32 % wdata [31:0] $end
$var reg 1 & we $end
$var integer 32 ' errors [31:0] $end
$var integer 32 ( i [31:0] $end
$scope module dut $end
$var wire 14 ) addr [13:0] $end
$var wire 1 # clk $end
$var wire 1 $ re $end
$var wire 32 * wdata [31:0] $end
$var wire 1 & we $end
$var wire 4 + word_sel [3:0] $end
$var wire 10 , row_addr [9:0] $end
$var reg 32 - rdata [31:0] $end
$upscope $end
$upscope $end
$enddefinitions $end
$comment Show the parameter values. $end
$dumpall
$end
#0
$dumpvars
b0 -
b0 ,
b0 +
b0 *
b0 )
bx (
b0 '
0&
b0 %
0$
0#
b0 "
b0 !
$end
#5000
1#
#10000
b10100101101001010000000000000001 %
b10100101101001010000000000000001 *
0#
b0 (
1&
#15000
1#
#16000
b1 (
#20000
b1 +
b10100101101001010000000000000010 %
b10100101101001010000000000000010 *
b1 "
b1 )
0#
#25000
1#
#26000
b10 (
#30000
b1111 +
b10100101101001010000000000000011 %
b10100101101001010000000000000011 *
b1111 "
b1111 )
0#
#35000
1#
#36000
b11 (
#40000
b1 ,
b0 +
b10100101101001010000000000000100 %
b10100101101001010000000000000100 *
b10000 "
b10000 )
0#
#45000
1#
#46000
b100 (
#50000
b110 ,
b100 +
b10100101101001010000000000000101 %
b10100101101001010000000000000101 *
b1100100 "
b1100100 )
0#
#55000
1#
#56000
b101 (
#60000
b111111 ,
b1111 +
b10100101101001010000000000000110 %
b10100101101001010000000000000110 *
b1111111111 "
b1111111111 )
0#
#65000
1#
#66000
b110 (
#70000
b11111111 ,
b10100101101001010000000000000111 %
b10100101101001010000000000000111 *
b111111111111 "
b111111111111 )
0#
#75000
1#
#76000
b111 (
#80000
b1111111111 ,
b10100101101001010000000000001000 %
b10100101101001010000000000001000 *
b11111111111111 "
b11111111111111 )
0#
#85000
1#
#86000
b1000 (
#90000
b10100101101001010000000000001000 !
b10100101101001010000000000001000 -
b0 (
1$
0&
0#
#95000
1#
#100000
b10100101101001010000000000000001 !
b10100101101001010000000000000001 -
b0 ,
b0 +
b0 "
b0 )
0#
#101000
b1 (
#105000
1#
#110000
b10100101101001010000000000000010 !
b10100101101001010000000000000010 -
b1 +
b1 "
b1 )
0#
#111000
b10 (
#115000
1#
#120000
b10100101101001010000000000000011 !
b10100101101001010000000000000011 -
b1111 +
b1111 "
b1111 )
0#
#121000
b11 (
#125000
1#
#130000
b10100101101001010000000000000100 !
b10100101101001010000000000000100 -
b1 ,
b0 +
b10000 "
b10000 )
0#
#131000
b100 (
#135000
1#
#140000
b10100101101001010000000000000101 !
b10100101101001010000000000000101 -
b110 ,
b100 +
b1100100 "
b1100100 )
0#
#141000
b101 (
#145000
1#
#150000
b10100101101001010000000000000110 !
b10100101101001010000000000000110 -
b111111 ,
b1111 +
b1111111111 "
b1111111111 )
0#
#151000
b110 (
#155000
1#
#160000
b10100101101001010000000000000111 !
b10100101101001010000000000000111 -
b11111111 ,
b111111111111 "
b111111111111 )
0#
#161000
b111 (
#165000
1#
#170000
b10100101101001010000000000001000 !
b10100101101001010000000000001000 -
b1111111111 ,
b11111111111111 "
b11111111111111 )
0#
#171000
b0 !
b0 -
0$
b1000 (
