1c/pipelined_3stage/mac_parallel_pipe3.sv
`timescale 1ns/1ps

module mac_parallel_pipe3 #(
    parameter W = 8,
    parameter N = 9
)(
    input  logic clk,
    input  logic reset_n,
    input  logic valid_in,

    input  logic signed [W-1:0] data0,
    input  logic signed [W-1:0] data1,
    input  logic signed [W-1:0] data2,
    input  logic signed [W-1:0] data3,
    input  logic signed [W-1:0] data4,
    input  logic signed [W-1:0] data5,
    input  logic signed [W-1:0] data6,
    input  logic signed [W-1:0] data7,
    input  logic signed [W-1:0] data8,

    input  logic signed [W-1:0] weight0,
    input  logic signed [W-1:0] weight1,
    input  logic signed [W-1:0] weight2,
    input  logic signed [W-1:0] weight3,
    input  logic signed [W-1:0] weight4,
    input  logic signed [W-1:0] weight5,
    input  logic signed [W-1:0] weight6,
    input  logic signed [W-1:0] weight7,
    input  logic signed [W-1:0] weight8,

    output logic signed [2*W+4:0] mac_out,
    output logic out_valid
);

    // =========================================================
    // STAGE 1
    // Nine parallel multipliers
    // =========================================================

    logic signed [2*W-1:0] product0_s1;
    logic signed [2*W-1:0] product1_s1;
    logic signed [2*W-1:0] product2_s1;
    logic signed [2*W-1:0] product3_s1;
    logic signed [2*W-1:0] product4_s1;
    logic signed [2*W-1:0] product5_s1;
    logic signed [2*W-1:0] product6_s1;
    logic signed [2*W-1:0] product7_s1;
    logic signed [2*W-1:0] product8_s1;

    // =========================================================
    // STAGE 2
    // Partial sums
    // =========================================================

    logic signed [2*W:0] sum01_s2;
    logic signed [2*W:0] sum23_s2;
    logic signed [2*W:0] sum45_s2;
    logic signed [2*W:0] sum67_s2;

    logic signed [2*W+1:0] sum0123_s2;
    logic signed [2*W+1:0] sum4567_s2;

    logic signed [2*W-1:0] product8_s2;

    // =========================================================
    // STAGE 3
    // Final result
    // =========================================================

    logic signed [2*W+2:0] sum_tree_s3;

    // Valid pipeline
    logic valid_s1;
    logic valid_s2;
    logic valid_s3;

    // =========================================================
    // Sequential pipeline
    // =========================================================

    always_ff @(posedge clk) begin

        if (!reset_n) begin

            // Stage 1
            product0_s1 <= '0;
            product1_s1 <= '0;
            product2_s1 <= '0;
            product3_s1 <= '0;
            product4_s1 <= '0;
            product5_s1 <= '0;
            product6_s1 <= '0;
            product7_s1 <= '0;
            product8_s1 <= '0;

            // Stage 2
            sum01_s2   <= '0;
            sum23_s2   <= '0;
            sum45_s2   <= '0;
            sum67_s2   <= '0;
            sum0123_s2 <= '0;
            sum4567_s2 <= '0;
            product8_s2 <= '0;

            // Stage 3
            sum_tree_s3 <= '0;

            // Valid pipeline
            valid_s1 <= 1'b0;
            valid_s2 <= 1'b0;
            valid_s3 <= 1'b0;

            mac_out   <= '0;
            out_valid <= 1'b0;

        end

        else begin

            // =================================================
            // STAGE 1
            // =================================================

            valid_s1 <= valid_in;

            if (valid_in) begin

                product0_s1 <= data0 * weight0;
                product1_s1 <= data1 * weight1;
                product2_s1 <= data2 * weight2;
                product3_s1 <= data3 * weight3;
                product4_s1 <= data4 * weight4;
                product5_s1 <= data5 * weight5;
                product6_s1 <= data6 * weight6;
                product7_s1 <= data7 * weight7;
                product8_s1 <= data8 * weight8;

            end

            // =================================================
            // STAGE 2
            // =================================================

            valid_s2 <= valid_s1;

            if (valid_s1) begin

                sum01_s2 <= product0_s1 + product1_s1;
                sum23_s2 <= product2_s1 + product3_s1;
                sum45_s2 <= product4_s1 + product5_s1;
                sum67_s2 <= product6_s1 + product7_s1;

                sum0123_s2 <=
                    (product0_s1 + product1_s1) +
                    (product2_s1 + product3_s1);

                sum4567_s2 <=
                    (product4_s1 + product5_s1) +
                    (product6_s1 + product7_s1);

                product8_s2 <= product8_s1;

            end

            // =================================================
            // STAGE 3
            // =================================================

            valid_s3 <= valid_s2;

            if (valid_s2) begin

                sum_tree_s3 <=
                    sum0123_s2 +
                    sum4567_s2 +
                    product8_s2;

                mac_out <=
                    sum0123_s2 +
                    sum4567_s2 +
                    product8_s2;

            end

            out_valid <= valid_s2;

        end

    end

endmodule

1c/pipelined_3stage/tb_mac_parallel_pipe3.sv
`timescale 1ns/1ps

module tb_mac_parallel_pipe3;

    logic clk;
    logic reset_n;
    logic valid_in;

    logic signed [7:0] data0;
    logic signed [7:0] data1;
    logic signed [7:0] data2;
    logic signed [7:0] data3;
    logic signed [7:0] data4;
    logic signed [7:0] data5;
    logic signed [7:0] data6;
    logic signed [7:0] data7;
    logic signed [7:0] data8;

    logic signed [7:0] weight0;
    logic signed [7:0] weight1;
    logic signed [7:0] weight2;
    logic signed [7:0] weight3;
    logic signed [7:0] weight4;
    logic signed [7:0] weight5;
    logic signed [7:0] weight6;
    logic signed [7:0] weight7;
    logic signed [7:0] weight8;

    logic signed [20:0] mac_out;
    logic out_valid;

    integer expected;

    // =========================================================
    // DUT
    // =========================================================

    mac_parallel_pipe3 dut (
        .clk(clk),
        .reset_n(reset_n),
        .valid_in(valid_in),

        .data0(data0),
        .data1(data1),
        .data2(data2),
        .data3(data3),
        .data4(data4),
        .data5(data5),
        .data6(data6),
        .data7(data7),
        .data8(data8),

        .weight0(weight0),
        .weight1(weight1),
        .weight2(weight2),
        .weight3(weight3),
        .weight4(weight4),
        .weight5(weight5),
        .weight6(weight6),
        .weight7(weight7),
        .weight8(weight8),

        .mac_out(mac_out),
        .out_valid(out_valid)
    );

    // =========================================================
    // CLOCK
    // =========================================================

    initial begin
        clk = 1'b0;
        forever #5 clk = ~clk;
    end

    // =========================================================
    // TEST
    // =========================================================

    initial begin

        $dumpfile("mac_parallel_pipe3.vcd");
        $dumpvars(0, tb_mac_parallel_pipe3);

        reset_n  = 1'b0;
        valid_in = 1'b0;

        data0 = 0;
        data1 = 0;
        data2 = 0;
        data3 = 0;
        data4 = 0;
        data5 = 0;
        data6 = 0;
        data7 = 0;
        data8 = 0;

        weight0 = 0;
        weight1 = 0;
        weight2 = 0;
        weight3 = 0;
        weight4 = 0;
        weight5 = 0;
        weight6 = 0;
        weight7 = 0;
        weight8 = 0;

        expected = 94;

        // =====================================================
        // RESET
        // =====================================================

        repeat (2) @(posedge clk);

        reset_n = 1'b1;

        // =====================================================
        // INPUT VECTOR
        // =====================================================

        @(negedge clk);

        data0 = 8'sd10;
        data1 = 8'sd20;
        data2 = -8'sd5;
        data3 = 8'sd7;
        data4 = 8'sd12;
        data5 = -8'sd8;
        data6 = 8'sd4;
        data7 = -8'sd10;
        data8 = 8'sd6;

        weight0 = 8'sd2;
        weight1 = 8'sd3;
        weight2 = 8'sd4;
        weight3 = -8'sd6;
        weight4 = 8'sd5;
        weight5 = -8'sd3;
        weight6 = 8'sd9;
        weight7 = 8'sd2;
        weight8 = -8'sd4;

        valid_in = 1'b1;

        // Stage 1
        @(posedge clk);

        // Remove valid after one input vector
        @(negedge clk);
        valid_in = 1'b0;

        // =====================================================
        // Wait for 3-stage pipeline
        // =====================================================

        repeat (2) @(posedge clk);

        #1;

        // =====================================================
        // CHECK
        // =====================================================

        if (out_valid && (mac_out == expected)) begin

            $display("");
            $display("==============================================");
            $display("       1(c)(ii) 3-STAGE PIPELINE PASSED");
            $display("==============================================");
            $display("Expected MAC = %0d", expected);
            $display("Actual MAC   = %0d", mac_out);
            $display("out_valid    = %b", out_valid);
            $display("==============================================");
            $display("");

        end
        else begin

            $display("");
            $display("==============================================");
            $display("       1(c)(ii) 3-STAGE PIPELINE FAILED");
            $display("==============================================");
            $display("Expected MAC = %0d", expected);
            $display("Actual MAC   = %0d", mac_out);
            $display("out_valid    = %b", out_valid);
            $display("==============================================");
            $display("");

        end

        #20;
        $finish;

    end

endmodule

1c/pipelined_3stage/mac_parallel_pipe3.vcd
$date
	Sat Sep 26 05:29:11 2026
$end
$version
	Icarus Verilog
$end
$timescale
	1ps
$end
$scope module tb_mac_parallel_pipe3 $end
$var wire 1 ! out_valid $end
$var wire 21 " mac_out [20:0] $end
$var reg 1 # clk $end
$var reg 8 $ data0 [7:0] $end
$var reg 8 % data1 [7:0] $end
$var reg 8 & data2 [7:0] $end
$var reg 8 ' data3 [7:0] $end
$var reg 8 ( data4 [7:0] $end
$var reg 8 ) data5 [7:0] $end
$var reg 8 * data6 [7:0] $end
$var reg 8 + data7 [7:0] $end
$var reg 8 , data8 [7:0] $end
$var reg 1 - reset_n $end
$var reg 1 . valid_in $end
$var reg 8 / weight0 [7:0] $end
$var reg 8 0 weight1 [7:0] $end
$var reg 8 1 weight2 [7:0] $end
$var reg 8 2 weight3 [7:0] $end
$var reg 8 3 weight4 [7:0] $end
$var reg 8 4 weight5 [7:0] $end
$var reg 8 5 weight6 [7:0] $end
$var reg 8 6 weight7 [7:0] $end
$var reg 8 7 weight8 [7:0] $end
$var integer 32 8 expected [31:0] $end
$scope module dut $end
$var wire 1 # clk $end
$var wire 8 9 data0 [7:0] $end
$var wire 8 : data1 [7:0] $end
$var wire 8 ; data2 [7:0] $end
$var wire 8 < data3 [7:0] $end
$var wire 8 = data4 [7:0] $end
$var wire 8 > data5 [7:0] $end
$var wire 8 ? data6 [7:0] $end
$var wire 8 @ data7 [7:0] $end
$var wire 8 A data8 [7:0] $end
$var wire 1 - reset_n $end
$var wire 1 . valid_in $end
$var wire 8 B weight0 [7:0] $end
$var wire 8 C weight1 [7:0] $end
$var wire 8 D weight2 [7:0] $end
$var wire 8 E weight3 [7:0] $end
$var wire 8 F weight4 [7:0] $end
$var wire 8 G weight5 [7:0] $end
$var wire 8 H weight6 [7:0] $end
$var wire 8 I weight7 [7:0] $end
$var wire 8 J weight8 [7:0] $end
$var parameter 32 K N $end
$var parameter 32 L W $end
$var reg 21 M mac_out [20:0] $end
$var reg 1 ! out_valid $end
$var reg 16 N product0_s1 [15:0] $end
$var reg 16 O product1_s1 [15:0] $end
$var reg 16 P product2_s1 [15:0] $end
$var reg 16 Q product3_s1 [15:0] $end
$var reg 16 R product4_s1 [15:0] $end
$var reg 16 S product5_s1 [15:0] $end
$var reg 16 T product6_s1 [15:0] $end
$var reg 16 U product7_s1 [15:0] $end
$var reg 16 V product8_s1 [15:0] $end
$var reg 16 W product8_s2 [15:0] $end
$var reg 18 X sum0123_s2 [17:0] $end
$var reg 17 Y sum01_s2 [16:0] $end
$var reg 17 Z sum23_s2 [16:0] $end
$var reg 18 [ sum4567_s2 [17:0] $end
$var reg 17 \ sum45_s2 [16:0] $end
$var reg 17 ] sum67_s2 [16:0] $end
$var reg 19 ^ sum_tree_s3 [18:0] $end
$var reg 1 _ valid_s1 $end
$var reg 1 ` valid_s2 $end
$var reg 1 a valid_s3 $end
$upscope $end
$upscope $end
$enddefinitions $end
$comment Show the parameter values. $end
$dumpall
b1000 L
b1001 K
$end
#0
$dumpvars
xa
x`
x_
bx ^
bx ]
bx \
bx [
bx Z
bx Y
bx X
bx W
bx V
bx U
bx T
bx S
bx R
bx Q
bx P
bx O
bx N
bx M
b0 J
b0 I
b0 H
b0 G
b0 F
b0 E
b0 D
b0 C
b0 B
b0 A
b0 @
b0 ?
b0 >
b0 =
b0 <
b0 ;
b0 :
b0 9
b1011110 8
b0 7
b0 6
b0 5
b0 4
b0 3
b0 2
b0 1
b0 0
b0 /
0.
0-
b0 ,
b0 +
b0 *
b0 )
b0 (
b0 '
b0 &
b0 %
b0 $
0#
bx "
x!
$end
#5000
0!
b0 "
b0 M
0a
0`
0_
b0 ^
b0 W
b0 [
b0 X
b0 ]
b0 \
b0 Z
b0 Y
b0 V
b0 U
b0 T
b0 S
b0 R
b0 Q
b0 P
b0 O
b0 N
1#
#10000
0#
#15000
1-
1#
#20000
1.
b11111100 7
b11111100 J
b10 6
b10 I
b1001 5
b1001 H
b11111101 4
b11111101 G
b101 3
b101 F
b11111010 2
b11111010 E
b100 1
b100 D
b11 0
b11 C
b10 /
b10 B
b110 ,
b110 A
b11110110 +
b11110110 @
b100 *
b100 ?
b11111000 )
b11111000 >
b1100 (
b1100 =
b111 '
b111 <
b11111011 &
b11111011 ;
b10100 %
b10100 :
b1010 $
b1010 9
0#
#25000
b1111111111101000 V
b1111111111101100 U
b100100 T
b11000 S
b111100 R
b1111111111010110 Q
b1111111111101100 P
b111100 O
b10100 N
1_
1#
#30000
0.
0#
#35000
b1111111111101000 W
b1100100 [
b10010 X
b10000 ]
b1010100 \
b11111111111000010 Z
b1010000 Y
1`
0_
1#
#40000
0#
#45000
1!
b1011110 "
b1011110 M
b1011110 ^
1a
0`
1#
#50000
0#
#55000
0!
0a
1#
