1b/mac_seq_b.sv
`timescale 1ns/1ps

module mac_seq_b #(
    parameter W = 8,
    parameter N = 9
)(
    input  logic clk,
    input  logic reset_n,

    // Weight loading phase
    input  logic load_weight,
    input  logic signed [W-1:0] weight_in,

    // Compute phase
    input  logic signed [W-1:0] data_in,

    output logic signed [2*W+4:0] mac_out,
    output logic out_valid
);

    // ------------------------------------------------
    // Local weight register file
    // ------------------------------------------------
    logic signed [W-1:0] kernel_buff [0:N-1];

    // ------------------------------------------------
    // Load and compute counters
    // ------------------------------------------------
    logic [3:0] load_idx;
    logic [3:0] comp_idx;

    // ------------------------------------------------
    // Current weight and multiplication
    // ------------------------------------------------
    logic signed [W-1:0] current_weight;
    logic signed [2*W-1:0] product;

    // ------------------------------------------------
    // Accumulator
    // ------------------------------------------------
    logic signed [2*W+4:0] accumulator;

    // Weight selected during compute
    assign current_weight = kernel_buff[comp_idx];

    // Signed multiplication
    assign product = data_in * current_weight;

    // ------------------------------------------------
    // Sequential logic
    // ------------------------------------------------
    always_ff @(posedge clk) begin

        if (!reset_n) begin

            load_idx   <= '0;
            comp_idx   <= '0;

            accumulator <= '0;
            mac_out     <= '0;

            out_valid <= 1'b0;

        end

        else begin

            // Default
            out_valid <= 1'b0;

            // ------------------------------------------------
            // WEIGHT LOAD PHASE
            // ------------------------------------------------
            if (load_weight) begin

                kernel_buff[load_idx] <= weight_in;

                if (load_idx == N-1) begin
                    load_idx <= '0;
                    comp_idx <= '0;
                    accumulator <= '0;
                end
                else begin
                    load_idx <= load_idx + 1'b1;
                end

            end

            // ------------------------------------------------
            // COMPUTE PHASE
            // ------------------------------------------------
            else begin

                if (comp_idx == N-1) begin

                    // Include final product
                    mac_out <= accumulator + product;

                    out_valid <= 1'b1;

                    // Prepare for next sequence
                    accumulator <= '0;
                    comp_idx <= '0;

                end

                else begin

                    accumulator <= accumulator + product;

                    comp_idx <= comp_idx + 1'b1;

                end

            end

        end

    end

endmodule

1b/tb_mac_seq_b.sv
`timescale 1ns/1ps

module tb_mac_seq_b;

    localparam W = 8;
    localparam N = 9;

    logic clk;
    logic reset_n;

    logic load_weight;

    logic signed [W-1:0] weight_in;
    logic signed [W-1:0] data_in;

    logic signed [2*W+4:0] mac_out;
    logic out_valid;

    integer expected;

    // ============================================================
    // DUT
    // ============================================================

    mac_seq_b #(
        .W(W),
        .N(N)
    ) dut (
        .clk(clk),
        .reset_n(reset_n),
        .load_weight(load_weight),
        .weight_in(weight_in),
        .data_in(data_in),
        .mac_out(mac_out),
        .out_valid(out_valid)
    );

    // ============================================================
    // CLOCK
    // ============================================================

    initial begin
        clk = 1'b0;
        forever #5 clk = ~clk;
    end

    // ============================================================
    // TEST
    // ============================================================

    initial begin

        // --------------------------------------------------------
        // Waveform
        // --------------------------------------------------------

        $dumpfile("mac_seq_b.vcd");
        $dumpvars(0, tb_mac_seq_b);

        // --------------------------------------------------------
        // Initial values
        // --------------------------------------------------------

        reset_n    = 1'b0;
        load_weight = 1'b0;
        weight_in  = '0;
        data_in    = '0;

        // Expected result:
        //
        // 10  *  2  =  20
        // 20  *  3  =  60
        // -5  *  4  = -20
        // 7   * -6  = -42
        // 12  *  5  =  60
        // -8  * -3  =  24
        // 4   *  9  =  36
        // -10 *  2  = -20
        // 6   * -4  = -24
        //
        // TOTAL = 94

        expected = 94;

        // ========================================================
        // RESET
        // ========================================================

        repeat (2) @(posedge clk);

        reset_n = 1'b1;

        // ========================================================
        // WEIGHT LOAD PHASE
        // ========================================================

        // Weight 0 = +2
        @(negedge clk);
        load_weight = 1'b1;
        weight_in = 8'sd2;

        // Weight 1 = +3
        @(negedge clk);
        weight_in = 8'sd3;

        // Weight 2 = +4
        @(negedge clk);
        weight_in = 8'sd4;

        // Weight 3 = -6
        @(negedge clk);
        weight_in = -8'sd6;

        // Weight 4 = +5
        @(negedge clk);
        weight_in = 8'sd5;

        // Weight 5 = -3
        @(negedge clk);
        weight_in = -8'sd3;

        // Weight 6 = +9
        @(negedge clk);
        weight_in = 8'sd9;

        // Weight 7 = +2
        @(negedge clk);
        weight_in = 8'sd2;

        // Weight 8 = -4
        @(negedge clk);
        weight_in = -8'sd4;

        // ========================================================
        // TRANSITION TO COMPUTE
        // ========================================================
        //
        // IMPORTANT:
        // Put the FIRST DATA VALUE here BEFORE the next
        // positive clock edge.
        //
        // This prevents an unwanted data=0 compute cycle.
        // ========================================================

        @(negedge clk);
        load_weight = 1'b0;
        weight_in   = '0;
        data_in     = 8'sd10;

        // ========================================================
        // COMPUTE PHASE
        // ========================================================

        // Data 0 = +10
        @(posedge clk);

        // Data 1 = +20
        @(negedge clk);
        data_in = 8'sd20;

        // Data 2 = -5
        @(negedge clk);
        data_in = -8'sd5;

        // Data 3 = +7
        @(negedge clk);
        data_in = 8'sd7;

        // Data 4 = +12
        @(negedge clk);
        data_in = 8'sd12;

        // Data 5 = -8
        @(negedge clk);
        data_in = -8'sd8;

        // Data 6 = +4
        @(negedge clk);
        data_in = 8'sd4;

        // Data 7 = -10
        @(negedge clk);
        data_in = -8'sd10;

        // Data 8 = +6
        @(negedge clk);
        data_in = 8'sd6;

        // ========================================================
        // 9th COMPUTE OPERATION
        // ========================================================

        @(posedge clk);

        // Allow nonblocking assignments to update
        #1;

        // ========================================================
        // CHECK RESULT IMMEDIATELY
        // ========================================================

        if (out_valid && (mac_out == expected)) begin

            $display("");
            $display("==============================================");
            $display("          ASSIGNMENT 1(b) TEST PASSED");
            $display("==============================================");
            $display("Expected MAC = %0d", expected);
            $display("Actual MAC   = %0d", mac_out);
            $display("out_valid    = %b", out_valid);
            $display("==============================================");
            $display("");

        end
        else begin

            $display("");
            $display("==============================================");
            $display("          ASSIGNMENT 1(b) TEST FAILED");
            $display("==============================================");
            $display("Expected MAC = %0d", expected);
            $display("Actual MAC   = %0d", mac_out);
            $display("out_valid    = %b", out_valid);
            $display("==============================================");
            $display("");

        end

        // Stop simulation
        #10;
        $finish;

    end

    // ============================================================
    // DEBUG OUTPUT
    // ============================================================

    always @(posedge clk) begin

        if (!reset_n) begin

            $display(
                "RESET | TIME=%0t ns",
                $time
            );

        end

        else if (load_weight) begin

            $display(
                "LOAD | TIME=%0t ns | index=%0d | weight=%0d",
                $time,
                dut.load_idx,
                weight_in
            );

        end

        else begin

            $display(
                "COMPUTE | TIME=%0t ns | index=%0d | data=%0d | weight=%0d | product=%0d | acc=%0d",
                $time,
                dut.comp_idx,
                data_in,
                dut.current_weight,
                dut.product,
                dut.accumulator
            );

        end

        if (out_valid) begin

            $display(
                "RESULT | TIME=%0t ns | MAC_OUT=%0d",
                $time,
                mac_out
            );

        end

    end

endmodule

1b/mac_seq_b.vcd
$date
	Sat Sep 26 05:16:52 2026
$end
$version
	Icarus Verilog
$end
$timescale
	1ps
$end
$scope module tb_mac_seq_b $end
$var wire 1 ! out_valid $end
$var wire 21 " mac_out [20:0] $end
$var parameter 32 # N $end
$var parameter 32 $ W $end
$var reg 1 % clk $end
$var reg 8 & data_in [7:0] $end
$var reg 1 ' load_weight $end
$var reg 1 ( reset_n $end
$var reg 8 ) weight_in [7:0] $end
$var integer 32 * expected [31:0] $end
$scope module dut $end
$var wire 1 % clk $end
$var wire 8 + current_weight [7:0] $end
$var wire 8 , data_in [7:0] $end
$var wire 1 ' load_weight $end
$var wire 1 ( reset_n $end
$var wire 8 - weight_in [7:0] $end
$var wire 16 . product [15:0] $end
$var parameter 32 / N $end
$var parameter 32 0 W $end
$var reg 21 1 accumulator [20:0] $end
$var reg 4 2 comp_idx [3:0] $end
$var reg 4 3 load_idx [3:0] $end
$var reg 21 4 mac_out [20:0] $end
$var reg 1 ! out_valid $end
$upscope $end
$upscope $end
$enddefinitions $end
$comment Show the parameter values. $end
$dumpall
b1000 0
b1001 /
b1000 $
b1001 #
$end
#0
$dumpvars
bx 4
bx 3
bx 2
bx 1
bx .
b0 -
b0 ,
bx +
b1011110 *
b0 )
0(
0'
b0 &
0%
bx "
x!
$end
#5000
0!
b0 "
b0 4
b0 1
b0 2
b0 3
1%
#10000
0%
#15000
1(
1%
#20000
b10 )
b10 -
1'
0%
#25000
b1 3
b0 .
b10 +
1%
#30000
b11 )
b11 -
0%
#35000
b10 3
1%
#40000
b100 )
b100 -
0%
#45000
b11 3
1%
#50000
b11111010 )
b11111010 -
0%
#55000
b100 3
1%
#60000
b101 )
b101 -
0%
#65000
b101 3
1%
#70000
b11111101 )
b11111101 -
0%
#75000
b110 3
1%
#80000
b1001 )
b1001 -
0%
#85000
b111 3
1%
#90000
b10 )
b10 -
0%
#95000
b1000 3
1%
#100000
b11111100 )
b11111100 -
0%
#105000
b0 3
1%
#110000
b10100 .
b1010 &
b1010 ,
b0 )
b0 -
0'
0%
#115000
b11110 .
b11 +
b1 2
b10100 1
1%
#120000
b111100 .
b10100 &
b10100 ,
0%
#125000
b1010000 .
b100 +
b10 2
b1010000 1
1%
#130000
b1111111111101100 .
b11111011 &
b11111011 ,
0%
#135000
b11110 .
b11111010 +
b11 2
b111100 1
1%
#140000
b1111111111010110 .
b111 &
b111 ,
0%
#145000
b100011 .
b101 +
b100 2
b10010 1
1%
#150000
b111100 .
b1100 &
b1100 ,
0%
#155000
b1111111111011100 .
b11111101 +
b101 2
b1001110 1
1%
#160000
b11000 .
b11111000 &
b11111000 ,
0%
#165000
b1111111110111000 .
b1001 +
b110 2
b1100110 1
1%
#170000
b100100 .
b100 &
b100 ,
0%
#175000
b1000 .
b10 +
b111 2
b10001010 1
1%
#180000
b1111111111101100 .
b11110110 &
b11110110 ,
0%
#185000
b101000 .
b11111100 +
b1000 2
b1110110 1
1%
#190000
b1111111111101000 .
b110 &
b110 ,
0%
#195000
b1100 .
b10 +
b0 2
b0 1
1!
b1011110 "
b1011110 4
1%
#200000
0%
#205000
b10010 .
b11 +
b1 2
b1100 1
0!
1%
