1a/mac_seq_a.sv
`timescale 1ns/1ps

module mac_seq_a #(
    parameter W = 8,
    parameter SEQ_LEN = 8
)(
    input  logic clk,
    input  logic reset_n,
    input  logic valid_in,

    input  logic signed [W-1:0] data_in,
    input  logic signed [W-1:0] weight_in,

    output logic signed [2*W+3:0] mac_out,
    output logic out_valid
);

    // Accumulator
    logic signed [2*W+3:0] accumulator;

    // Counts valid input samples
    logic [3:0] count;

    // 8-bit signed × 8-bit signed = 16-bit signed product
    logic signed [2*W-1:0] product;

    assign product = data_in * weight_in;

    always_ff @(posedge clk) begin

        if (!reset_n) begin
            accumulator <= '0;
            count       <= '0;
            mac_out     <= '0;
            out_valid   <= 1'b0;
        end

        else begin

            // Default value
            out_valid <= 1'b0;

            if (valid_in) begin

                // Last sample of 8-sample sequence
                if (count == SEQ_LEN-1) begin

                    // Include the 8th multiplication
                    mac_out <= accumulator + product;

                    out_valid <= 1'b1;

                    // Prepare for next MAC sequence
                    accumulator <= '0;
                    count       <= '0;

                end

                else begin

                    accumulator <= accumulator + product;
                    count       <= count + 1'b1;

                end

            end

        end

    end

endmodule

1a/tb_mac_seq_a.sv
`timescale 1ns/1ps

module tb_mac_seq_a;

    localparam W = 8;
    localparam SEQ_LEN = 8;

    logic clk;
    logic reset_n;
    logic valid_in;

    logic signed [W-1:0] data_in;
    logic signed [W-1:0] weight_in;

    logic signed [2*W+3:0] mac_out;
    logic out_valid;

    integer expected;

    // DUT
    mac_seq_a #(
        .W(W),
        .SEQ_LEN(SEQ_LEN)
    ) dut (
        .clk(clk),
        .reset_n(reset_n),
        .valid_in(valid_in),
        .data_in(data_in),
        .weight_in(weight_in),
        .mac_out(mac_out),
        .out_valid(out_valid)
    );

    // 10 ns clock
    initial begin
        clk = 1'b0;
        forever #5 clk = ~clk;
    end

    initial begin
        $dumpfile("mac_seq_a.vcd");
        $dumpvars(0, tb_mac_seq_a);

        reset_n   = 1'b0;
        valid_in  = 1'b0;
        data_in   = '0;
        weight_in = '0;

        // Expected result:
        // 10*2 + 20*3 + (-5)*4 + 7*(-6)
        // + 12*5 + (-8)*(-3) + 4*9 + (-10)*2
        expected = 118;

        // Reset
        repeat (2) @(posedge clk);

        reset_n = 1'b1;

        // ------------------------------------------------
        // Input 1
        // 10 × 2 = 20
        // ------------------------------------------------
        @(negedge clk);
        valid_in  = 1'b1;
        data_in   = 8'sd10;
        weight_in = 8'sd2;

        // ------------------------------------------------
        // Input 2
        // 20 × 3 = 60
        // ------------------------------------------------
        @(negedge clk);
        data_in   = 8'sd20;
        weight_in = 8'sd3;

        // ------------------------------------------------
        // Input 3
        // -5 × 4 = -20
        // ------------------------------------------------
        @(negedge clk);
        data_in   = -8'sd5;
        weight_in = 8'sd4;

        // ------------------------------------------------
        // Input 4
        // 7 × -6 = -42
        // ------------------------------------------------
        @(negedge clk);
        data_in   = 8'sd7;
        weight_in = -8'sd6;

        // ------------------------------------------------
        // Input 5
        // 12 × 5 = 60
        // ------------------------------------------------
        @(negedge clk);
        data_in   = 8'sd12;
        weight_in = 8'sd5;

        // ------------------------------------------------
        // Input 6
        // -8 × -3 = 24
        // ------------------------------------------------
        @(negedge clk);
        data_in   = -8'sd8;
        weight_in = -8'sd3;

        // ------------------------------------------------
        // Input 7
        // 4 × 9 = 36
        // ------------------------------------------------
        @(negedge clk);
        data_in   = 8'sd4;
        weight_in = 8'sd9;

        // ------------------------------------------------
        // Input 8
        // -10 × 2 = -20
        // ------------------------------------------------
        @(negedge clk);
        data_in   = -8'sd10;
        weight_in = 8'sd2;

        // 8th MAC operation
        @(posedge clk);

        // Stop inputs
        @(negedge clk);
        valid_in  = 1'b0;
        data_in   = '0;
        weight_in = '0;

        // Check result
        @(posedge clk);

        if (mac_out == expected) begin
            $display("");
            $display("==============================================");
            $display("              TEST PASSED");
            $display("==============================================");
            $display("Expected MAC = %0d", expected);
            $display("Actual MAC   = %0d", mac_out);
            $display("==============================================");
            $display("");
        end
        else begin
            $display("");
            $display("==============================================");
            $display("              TEST FAILED");
            $display("==============================================");
            $display("Expected MAC = %0d", expected);
            $display("Actual MAC   = %0d", mac_out);
            $display("==============================================");
            $display("");
        end

        #10;
        $finish;

    end

    // Debug information
    always @(posedge clk) begin

        if (valid_in) begin
            $display(
                "TIME=%0t ns | DATA=%0d | WEIGHT=%0d | PRODUCT=%0d | COUNT=%0d | ACC=%0d",
                $time,
                data_in,
                weight_in,
                data_in * weight_in,
                dut.count,
                dut.accumulator
            );
        end

        if (out_valid) begin
            $display(
                "TIME=%0t ns | MAC COMPLETE | MAC_OUT=%0d",
                $time,
                mac_out
            );
        end

    end

endmodule

1a/mac_seq_a.vcd
$date
	Sat Sep 26 05:01:23 2026
$end
$version
	Icarus Verilog
$end
$timescale
	1ps
$end
$scope module tb_mac_seq_a $end
$var wire 1 ! out_valid $end
$var wire 20 " mac_out [19:0] $end
$var parameter 32 # SEQ_LEN $end
$var parameter 32 $ W $end
$var reg 1 % clk $end
$var reg 8 & data_in [7:0] $end
$var reg 1 ' reset_n $end
$var reg 1 ( valid_in $end
$var reg 8 ) weight_in [7:0] $end
$var integer 32 * expected [31:0] $end
$scope module dut $end
$var wire 1 % clk $end
$var wire 8 + data_in [7:0] $end
$var wire 1 ' reset_n $end
$var wire 1 ( valid_in $end
$var wire 8 , weight_in [7:0] $end
$var wire 16 - product [15:0] $end
$var parameter 32 . SEQ_LEN $end
$var parameter 32 / W $end
$var reg 20 0 accumulator [19:0] $end
$var reg 4 1 count [3:0] $end
$var reg 20 2 mac_out [19:0] $end
$var reg 1 ! out_valid $end
$upscope $end
$upscope $end
$enddefinitions $end
$comment Show the parameter values. $end
$dumpall
b1000 /
b1000 .
b1000 $
b1000 #
$end
#0
$dumpvars
bx 2
bx 1
bx 0
b0 -
b0 ,
b0 +
b1110110 *
b0 )
0(
0'
b0 &
0%
bx "
x!
$end
#5000
0!
b0 "
b0 2
b0 1
b0 0
1%
#10000
0%
#15000
1'
1%
#20000
b10100 -
b10 )
b10 ,
b1010 &
b1010 +
1(
0%
#25000
b1 1
b10100 0
1%
#30000
b11 )
b11 ,
b111100 -
b10100 &
b10100 +
0%
#35000
b10 1
b1010000 0
1%
#40000
b100 )
b100 ,
b1111111111101100 -
b11111011 &
b11111011 +
0%
#45000
b11 1
b111100 0
1%
#50000
b11111010 )
b11111010 ,
b1111111111010110 -
b111 &
b111 +
0%
#55000
b100 1
b10010 0
1%
#60000
b101 )
b101 ,
b111100 -
b1100 &
b1100 +
0%
#65000
b101 1
b1001110 0
1%
#70000
b11111101 )
b11111101 ,
b11000 -
b11111000 &
b11111000 +
0%
#75000
b110 1
b1100110 0
1%
#80000
b1001 )
b1001 ,
b100100 -
b100 &
b100 +
0%
#85000
b111 1
b10001010 0
1%
#90000
b10 )
b10 ,
b1111111111101100 -
b11110110 &
b11110110 +
0%
#95000
b0 1
b0 0
1!
b1110110 "
b1110110 2
1%
#100000
b0 )
b0 ,
b0 -
b0 &
b0 +
0(
0%
#105000
0!
1%
